toml_schema/__init__.py
toml_schema/py.typed
toml_schema-0.0.1.dist-info/LICENSE
toml_schema-0.0.1.dist-info/METADATA
toml_schema-0.0.1.dist-info/WHEEL
toml_schema-0.0.1.dist-info/entry_points.txt
toml_schema-0.0.1.dist-info/top_level.txt
toml_schema-0.0.1.dist-info/RECORD
